free_torrents/__init__.py
free_torrents/fedora.py
free_torrents/qubes.py
free_torrents-1.4.0.dist-info/COPYING
free_torrents-1.4.0.dist-info/METADATA
free_torrents-1.4.0.dist-info/WHEEL
free_torrents-1.4.0.dist-info/entry_points.txt
free_torrents-1.4.0.dist-info/top_level.txt
free_torrents-1.4.0.dist-info/RECORD
