Metadata-Version: 2.1
Name: free-torrents
Version: 1.4.0
Summary: Script to facilitate downloading free (as-in-speech) torrents
Home-page: https://legoktm.com/w/index.php?title=free-torrents
Author: Kunal Mehta
Author-email: legoktm@debian.org
License: GPL-3.0-or-later
Requires-Python: >= 3.9
License-File: COPYING
Requires-Dist: requests
